<page x="0" y="0" dx="0" dy="0">
<block x="0" y="0" dx="0" dy="0">
<line x="1183" y="0" dx="-1182" dy="0" value="0">
 <space x="1183" y="495" dx="-601" dy="16" />
 <space x="583" y="495" dx="-4" dy="16" />
 <space x="580" y="495" dx="-4" dy="16" />
 <space x="577" y="495" dx="-3" dy="16" />
 <space x="576" y="495" dx="-4" dy="16" />
 <space x="575" y="495" dx="-4" dy="16" />
 <space x="575" y="495" dx="-4" dy="16" />
 <space x="575" y="495" dx="-3" dy="16" />
 <space x="576" y="495" dx="-3" dy="16" />
 <space x="577" y="495" dx="-3" dy="16" />
 <space x="578" y="495" dx="-3" dy="16" />
 <space x="579" y="495" dx="-3" dy="16" />
 <space x="580" y="495" dx="-3" dy="16" />
 <space x="581" y="495" dx="-3" dy="16" />
 <space x="582" y="495" dx="-4" dy="16" />
 <space x="582" y="495" dx="-3" dy="16" />
 <space x="583" y="495" dx="-4" dy="16" />
 <space x="583" y="495" dx="-4" dy="16" />
 <space x="583" y="495" dx="-3" dy="16" />
 <space x="584" y="495" dx="-4" dy="16" />
 <space x="584" y="495" dx="-4" dy="16" />
 <space x="584" y="495" dx="-4" dy="16" />
 <space x="584" y="495" dx="-3" dy="16" />
 <space x="585" y="495" dx="-4" dy="16" />
 <space x="585" y="495" dx="-4" dy="16" />
 <space x="585" y="495" dx="-4" dy="16" />
 <space x="585" y="495" dx="-4" dy="16" />
 <space x="585" y="495" dx="-3" dy="16" />
 <space x="583" y="495" dx="15" dy="16" />
 <box x="583" y="495" dx="15" dy="16" value="_" />
 <box x="602" y="92" dx="23" dy="634" value="(PICTURE)" />
</line>
<line x="316" y="35" dx="638" dy="24" value="1">
 <space x="316" y="37" dx="-4" dy="23" />
 <space x="313" y="37" dx="-3" dy="23" />
 <space x="312" y="37" dx="-3" dy="23" />
 <space x="312" y="37" dx="-3" dy="23" />
 <space x="313" y="37" dx="-4" dy="23" />
 <space x="313" y="37" dx="-3" dy="23" />
 <space x="315" y="37" dx="-4" dy="23" />
 <space x="316" y="37" dx="-4" dy="23" />
 <space x="316" y="37" dx="-3" dy="23" />
 <space x="317" y="37" dx="-4" dy="23" />
 <space x="317" y="37" dx="-3" dy="23" />
 <space x="318" y="37" dx="-4" dy="23" />
 <space x="318" y="37" dx="-3" dy="23" />
 <space x="319" y="37" dx="-4" dy="23" />
 <space x="316" y="37" dx="13" dy="23" />
 <box x="316" y="37" dx="13" dy="23" value="f" numac="2" weights="99,99" achars="f,F" />
 <box x="332" y="43" dx="14" dy="17" value="u" numac="1" weights="97" achars="u" />
 <box x="350" y="43" dx="14" dy="17" value="n" numac="1" weights="96" achars="n" />
 <box x="368" y="43" dx="14" dy="17" value="n" numac="1" weights="96" achars="n" />
 <box x="385" y="43" dx="15" dy="17" value="g" numac="2" weights="98,96" achars="g,e" />
 <box x="403" y="36" dx="3" dy="24" value="l" numac="4" weights="98,95,95,86" achars="l,I,|,1" />
 <space x="407" y="36" dx="28" dy="24" />
 <box x="436" y="36" dx="4" dy="24" value="l" numac="5" weights="98,96,95,90,85" achars="l,f,I,1,r" />
 <box x="443" y="43" dx="16" dy="17" value="o" numac="2" weights="99,97" achars="o,0" />
 <box x="460" y="39" dx="10" dy="21" value="t" numac="1" weights="98" achars="t" />
 <space x="471" y="43" dx="6" dy="17" />
 <box x="478" y="43" dx="23" dy="17" value="w" numac="1" weights="98" achars="w" />
 <box x="503" y="37" dx="4" dy="23" value="i" numac="1" weights="100" achars="i" />
 <box x="510" y="39" dx="10" dy="21" value="t" numac="1" weights="98" achars="t" />
 <box x="522" y="36" dx="14" dy="24" value="h" numac="1" weights="98" achars="h" />
 <space x="537" y="43" dx="27" dy="17" />
 <box x="565" y="43" dx="11" dy="17" value="s" numac="2" weights="98,94" achars="s,5" />
 <box x="578" y="43" dx="14" dy="17" value="g" numac="2" weights="98,96" achars="g,e" />
 <box x="595" y="43" dx="14" dy="17" value="u" numac="1" weights="97" achars="u" />
 <box x="613" y="36" dx="15" dy="24" value="d" numac="1" weights="99" achars="d" />
 <box x="631" y="43" dx="16" dy="17" value="o" numac="2" weights="99,97" achars="o,0" />
 <space x="648" y="38" dx="7" dy="22" />
 <box x="656" y="38" dx="15" dy="22" value="9" numac="2" weights="99,96" achars="9,g" />
 <box x="673" y="38" dx="14" dy="22" value="5" numac="1" weights="99" achars="5" />
 <box x="689" y="38" dx="11" dy="13" value="O" numac="3" weights="99,99,93" achars="O,0,a" />
 <box x="694" y="37" dx="15" dy="23" value="/" numac="1" weights="99" achars="/" />
 <box x="703" y="46" dx="11" dy="14" value="o" numac="3" weights="99,97,95" achars="o,0,a" />
 <space x="715" y="43" dx="6" dy="17" />
 <box x="722" y="43" dx="13" dy="17" value="c" numac="1" weights="98" achars="c" />
 <box x="737" y="43" dx="16" dy="17" value="o" numac="3" weights="99,98,98" achars="o,O,0" />
 <box x="756" y="43" dx="14" dy="17" value="n" numac="1" weights="96" achars="n" />
 <box x="773" y="35" dx="10" dy="25" value="f" numac="1" weights="100" achars="f" />
 <box x="784" y="37" dx="4" dy="23" value="i" numac="1" weights="100" achars="i" />
 <box x="791" y="36" dx="15" dy="24" value="d" numac="1" weights="99" achars="d" />
 <box x="809" y="43" dx="15" dy="17" value="g" numac="2" weights="98,96" achars="g,e" />
 <box x="827" y="43" dx="14" dy="17" value="n" numac="1" weights="96" achars="n" />
 <box x="844" y="43" dx="12" dy="17" value="c" numac="1" weights="98" achars="c" />
 <box x="859" y="43" dx="14" dy="17" value="g" numac="2" weights="98,96" achars="g,e" />
 <space x="874" y="36" dx="8" dy="24" />
 <box x="883" y="36" dx="3" dy="24" value="l" numac="4" weights="98,95,95,90" achars="l,I,|,1" />
 <box x="891" y="37" dx="3" dy="23" value="i" numac="1" weights="100" achars="i" />
 <box x="898" y="43" dx="24" dy="17" value="m" numac="1" weights="99" achars="m" />
 <box x="925" y="37" dx="4" dy="23" value="i" numac="1" weights="100" achars="i" />
 <box x="932" y="39" dx="10" dy="21" value="t" numac="1" weights="99" achars="t" />
 <box x="944" y="43" dx="10" dy="17" value="s" numac="2" weights="98,94" achars="s,5" />
</line>
<line x="71" y="86" dx="20" dy="23" value="2">
 <space x="74" y="86" dx="-1" dy="14" />
 <space x="71" y="86" dx="20" dy="14" />
 <box x="71" y="86" dx="20" dy="14" value="O" numac="2" weights="99,99" achars="O,0" />
</line>
<line x="587" y="105" dx="53" dy="28" value="3">
 <space x="123" y="113" dx="13" dy="16" />
 <space x="169" y="113" dx="12" dy="16" />
 <space x="225" y="113" dx="11" dy="16" />
 <space x="287" y="113" dx="9" dy="16" />
 <space x="349" y="113" dx="6" dy="16" />
 <space x="406" y="113" dx="4" dy="16" />
 <space x="455" y="113" dx="3" dy="16" />
 <space x="496" y="113" dx="1" dy="16" />
 <space x="527" y="113" dx="-1" dy="16" />
 <space x="549" y="113" dx="-2" dy="16" />
 <space x="564" y="113" dx="-2" dy="16" />
 <space x="574" y="113" dx="-3" dy="16" />
 <space x="580" y="113" dx="-3" dy="16" />
 <space x="584" y="113" dx="-4" dy="16" />
 <space x="585" y="113" dx="-3" dy="16" />
 <space x="587" y="113" dx="-4" dy="16" />
 <space x="587" y="113" dx="-4" dy="16" />
 <space x="587" y="113" dx="-3" dy="16" />
 <space x="588" y="113" dx="-4" dy="16" />
 <space x="588" y="113" dx="-4" dy="16" />
 <space x="588" y="113" dx="-4" dy="16" />
 <space x="588" y="113" dx="-3" dy="16" />
 <space x="589" y="113" dx="-4" dy="16" />
 <space x="589" y="113" dx="-4" dy="16" />
 <space x="589" y="113" dx="-4" dy="16" />
 <space x="589" y="113" dx="-4" dy="16" />
 <space x="589" y="113" dx="-3" dy="16" />
 <space x="590" y="113" dx="-4" dy="16" />
 <space x="587" y="113" dx="12" dy="16" />
 <box x="587" y="113" dx="12" dy="16" value="/" numac="1" weights="98" achars="/" />
 <space x="600" y="114" dx="27" dy="15" />
 <box x="628" y="114" dx="12" dy="15" value="\" numac="2" weights="98,86" achars="\,1" />
</line>
<line x="571" y="125" dx="85" dy="28" value="4">
 <space x="571" y="134" dx="-4" dy="15" />
 <space x="568" y="134" dx="-4" dy="15" />
 <space x="566" y="134" dx="-4" dy="15" />
 <space x="564" y="134" dx="-3" dy="15" />
 <space x="564" y="134" dx="-4" dy="15" />
 <space x="563" y="134" dx="-3" dy="15" />
 <space x="564" y="134" dx="-4" dy="15" />
 <space x="564" y="134" dx="-3" dy="15" />
 <space x="566" y="134" dx="-4" dy="15" />
 <space x="567" y="134" dx="-4" dy="15" />
 <space x="568" y="134" dx="-4" dy="15" />
 <space x="569" y="134" dx="-4" dy="15" />
 <space x="569" y="134" dx="-3" dy="15" />
 <space x="570" y="134" dx="-4" dy="15" />
 <space x="570" y="134" dx="-3" dy="15" />
 <space x="571" y="134" dx="-4" dy="15" />
 <space x="571" y="134" dx="-3" dy="15" />
 <space x="572" y="134" dx="-4" dy="15" />
 <space x="572" y="134" dx="-4" dy="15" />
 <space x="572" y="134" dx="-4" dy="15" />
 <space x="572" y="134" dx="-3" dy="15" />
 <space x="573" y="134" dx="-4" dy="15" />
 <space x="573" y="134" dx="-4" dy="15" />
 <space x="573" y="134" dx="-4" dy="15" />
 <space x="573" y="134" dx="-4" dy="15" />
 <space x="573" y="134" dx="-3" dy="15" />
 <space x="574" y="134" dx="-4" dy="15" />
 <space x="571" y="134" dx="12" dy="15" />
 <box x="571" y="134" dx="12" dy="15" value="/" numac="2" weights="98,91" achars="/,l" />
 <space x="584" y="134" dx="17" dy="15" />
 <space x="617" y="134" dx="11" dy="15" />
 <space x="641" y="134" dx="2" dy="15" />
 <box x="644" y="134" dx="12" dy="15" value="\" numac="1" weights="98" achars="\" />
</line>
<line x="556" y="145" dx="115" dy="28" value="5">
 <space x="556" y="155" dx="-4" dy="15" />
 <space x="553" y="155" dx="-4" dy="15" />
 <space x="551" y="155" dx="-4" dy="15" />
 <space x="549" y="155" dx="-3" dy="15" />
 <space x="549" y="155" dx="-4" dy="15" />
 <space x="549" y="155" dx="-4" dy="15" />
 <space x="549" y="155" dx="-3" dy="15" />
 <space x="550" y="155" dx="-3" dy="15" />
 <space x="551" y="155" dx="-3" dy="15" />
 <space x="552" y="155" dx="-3" dy="15" />
 <space x="553" y="155" dx="-3" dy="15" />
 <space x="554" y="155" dx="-3" dy="15" />
 <space x="555" y="155" dx="-4" dy="15" />
 <space x="555" y="155" dx="-3" dy="15" />
 <space x="556" y="155" dx="-4" dy="15" />
 <space x="556" y="155" dx="-4" dy="15" />
 <space x="556" y="155" dx="-3" dy="15" />
 <space x="557" y="155" dx="-4" dy="15" />
 <space x="557" y="155" dx="-4" dy="15" />
 <space x="557" y="155" dx="-3" dy="15" />
 <space x="558" y="155" dx="-4" dy="15" />
 <space x="558" y="155" dx="-4" dy="15" />
 <space x="558" y="155" dx="-4" dy="15" />
 <space x="558" y="155" dx="-4" dy="15" />
 <space x="558" y="155" dx="-3" dy="15" />
 <space x="559" y="155" dx="-4" dy="15" />
 <space x="556" y="155" dx="12" dy="15" />
 <box x="556" y="155" dx="12" dy="15" value="/" numac="2" weights="98,97" achars="/,r" />
 <space x="569" y="155" dx="19" dy="15" />
 <space x="607" y="155" dx="14" dy="15" />
 <space x="642" y="155" dx="6" dy="15" />
 <space x="658" y="155" dx="0" dy="15" />
 <box x="659" y="155" dx="12" dy="15" value="\" numac="2" weights="98,86" achars="\,1" />
</line>
<line x="540" y="165" dx="147" dy="28" value="6">
 <space x="540" y="175" dx="-4" dy="15" />
 <space x="537" y="175" dx="-4" dy="15" />
 <space x="535" y="175" dx="-4" dy="15" />
 <space x="533" y="175" dx="-3" dy="15" />
 <space x="533" y="175" dx="-4" dy="15" />
 <space x="533" y="175" dx="-4" dy="15" />
 <space x="533" y="175" dx="-3" dy="15" />
 <space x="534" y="175" dx="-3" dy="15" />
 <space x="535" y="175" dx="-3" dy="15" />
 <space x="537" y="175" dx="-4" dy="15" />
 <space x="537" y="175" dx="-3" dy="15" />
 <space x="538" y="175" dx="-3" dy="15" />
 <space x="539" y="175" dx="-4" dy="15" />
 <space x="539" y="175" dx="-3" dy="15" />
 <space x="540" y="175" dx="-4" dy="15" />
 <space x="540" y="175" dx="-3" dy="15" />
 <space x="541" y="175" dx="-4" dy="15" />
 <space x="541" y="175" dx="-4" dy="15" />
 <space x="541" y="175" dx="-3" dy="15" />
 <space x="542" y="175" dx="-4" dy="15" />
 <space x="542" y="175" dx="-4" dy="15" />
 <space x="542" y="175" dx="-4" dy="15" />
 <space x="542" y="175" dx="-4" dy="15" />
 <space x="542" y="175" dx="-3" dy="15" />
 <space x="543" y="175" dx="-4" dy="15" />
 <space x="540" y="175" dx="12" dy="15" />
 <box x="540" y="175" dx="12" dy="15" value="/" numac="2" weights="98,91" achars="/,l" />
 <space x="553" y="175" dx="16" dy="15" />
 <space x="588" y="175" dx="14" dy="15" />
 <space x="628" y="175" dx="8" dy="15" />
 <space x="657" y="175" dx="3" dy="15" />
 <space x="672" y="175" dx="-1" dy="15" />
 <space x="677" y="175" dx="-3" dy="15" />
 <box x="675" y="175" dx="12" dy="15" value="\" numac="1" weights="98" achars="\" />
</line>
<line x="71" y="194" dx="631" dy="19" value="7">
 <space x="74" y="201" dx="-1" dy="13" />
 <space x="71" y="201" dx="20" dy="13" />
 <box x="71" y="201" dx="20" dy="13" value="N" numac="1" weights="96" achars="N" />
 <box x="87" y="216" dx="4" dy="4" value="." numac="2" weights="99,96" achars=".,," />
 <space x="92" y="196" dx="15" dy="15" />
 <space x="127" y="196" dx="15" dy="15" />
 <space x="178" y="196" dx="13" dy="15" />
 <space x="237" y="196" dx="12" dy="15" />
 <space x="300" y="196" dx="9" dy="15" />
 <space x="359" y="196" dx="6" dy="15" />
 <space x="410" y="196" dx="3" dy="15" />
 <space x="450" y="196" dx="1" dy="15" />
 <space x="479" y="196" dx="0" dy="15" />
 <space x="499" y="196" dx="-2" dy="15" />
 <space x="511" y="196" dx="-2" dy="15" />
 <space x="519" y="196" dx="-4" dy="15" />
 <space x="522" y="196" dx="-3" dy="15" />
 <space x="524" y="196" dx="-3" dy="15" />
 <space x="525" y="196" dx="-3" dy="15" />
 <space x="526" y="196" dx="-4" dy="15" />
 <space x="526" y="196" dx="-4" dy="15" />
 <space x="526" y="196" dx="-3" dy="15" />
 <space x="527" y="196" dx="-4" dy="15" />
 <space x="527" y="196" dx="-4" dy="15" />
 <space x="527" y="196" dx="-4" dy="15" />
 <space x="527" y="196" dx="-3" dy="15" />
 <box x="525" y="196" dx="12" dy="15" value="/" numac="2" weights="100,93" achars="/,r" />
 <space x="538" y="196" dx="18" dy="15" />
 <space x="576" y="196" dx="15" dy="15" />
 <space x="620" y="196" dx="11" dy="15" />
 <space x="658" y="196" dx="4" dy="15" />
 <space x="680" y="196" dx="0" dy="15" />
 <space x="689" y="196" dx="-2" dy="15" />
 <space x="692" y="196" dx="-3" dy="15" />
 <box x="690" y="196" dx="12" dy="15" value="\" numac="2" weights="100,87" achars="\,1" />
</line>
<line x="87" y="206" dx="631" dy="28" value="8">
 <space x="509" y="216" dx="-4" dy="15" />
 <space x="506" y="216" dx="-4" dy="15" />
 <space x="504" y="216" dx="-4" dy="15" />
 <space x="502" y="216" dx="-3" dy="15" />
 <space x="502" y="216" dx="-3" dy="15" />
 <space x="503" y="216" dx="-4" dy="15" />
 <space x="503" y="216" dx="-3" dy="15" />
 <space x="504" y="216" dx="-3" dy="15" />
 <space x="505" y="216" dx="-3" dy="15" />
 <space x="506" y="216" dx="-3" dy="15" />
 <space x="507" y="216" dx="-3" dy="15" />
 <space x="508" y="216" dx="-4" dy="15" />
 <space x="508" y="216" dx="-3" dy="15" />
 <space x="509" y="216" dx="-4" dy="15" />
 <space x="509" y="216" dx="-3" dy="15" />
 <space x="510" y="216" dx="-4" dy="15" />
 <space x="510" y="216" dx="-4" dy="15" />
 <space x="510" y="216" dx="-4" dy="15" />
 <space x="510" y="216" dx="-3" dy="15" />
 <space x="511" y="216" dx="-4" dy="15" />
 <space x="511" y="216" dx="-4" dy="15" />
 <space x="511" y="216" dx="-4" dy="15" />
 <space x="511" y="216" dx="-3" dy="15" />
 <space x="512" y="216" dx="-4" dy="15" />
 <space x="509" y="216" dx="12" dy="15" />
 <box x="509" y="216" dx="12" dy="15" value="/" numac="2" weights="98,91" achars="/,l" />
 <space x="522" y="216" dx="16" dy="15" />
 <space x="557" y="216" dx="15" dy="15" />
 <space x="603" y="216" dx="11" dy="15" />
 <space x="646" y="216" dx="6" dy="15" />
 <space x="677" y="216" dx="3" dy="15" />
 <space x="696" y="216" dx="-1" dy="15" />
 <space x="704" y="216" dx="-2" dy="15" />
 <space x="707" y="216" dx="-3" dy="15" />
 <space x="708" y="216" dx="-3" dy="15" />
 <box x="706" y="216" dx="12" dy="15" value="\" numac="1" weights="98" achars="\" />
</line>
<line x="494" y="227" dx="239" dy="28" value="9">
 <space x="494" y="237" dx="-4" dy="15" />
 <space x="491" y="237" dx="-4" dy="15" />
 <space x="489" y="237" dx="-4" dy="15" />
 <space x="487" y="237" dx="-3" dy="15" />
 <space x="487" y="237" dx="-3" dy="15" />
 <space x="488" y="237" dx="-4" dy="15" />
 <space x="488" y="237" dx="-3" dy="15" />
 <space x="489" y="237" dx="-3" dy="15" />
 <space x="490" y="237" dx="-3" dy="15" />
 <space x="491" y="237" dx="-3" dy="15" />
 <space x="492" y="237" dx="-3" dy="15" />
 <space x="493" y="237" dx="-4" dy="15" />
 <space x="493" y="237" dx="-3" dy="15" />
 <space x="494" y="237" dx="-4" dy="15" />
 <space x="494" y="237" dx="-3" dy="15" />
 <space x="495" y="237" dx="-4" dy="15" />
 <space x="495" y="237" dx="-4" dy="15" />
 <space x="495" y="237" dx="-3" dy="15" />
 <space x="496" y="237" dx="-4" dy="15" />
 <space x="496" y="237" dx="-4" dy="15" />
 <space x="496" y="237" dx="-4" dy="15" />
 <space x="496" y="237" dx="-3" dy="15" />
 <space x="497" y="237" dx="-4" dy="15" />
 <space x="494" y="237" dx="12" dy="15" />
 <box x="494" y="237" dx="12" dy="15" value="/" numac="2" weights="98,97" achars="/,r" />
 <space x="507" y="237" dx="15" dy="15" />
 <space x="541" y="237" dx="14" dy="15" />
 <space x="586" y="237" dx="11" dy="15" />
 <space x="632" y="237" dx="7" dy="15" />
 <space x="670" y="237" dx="4" dy="15" />
 <space x="697" y="237" dx="0" dy="15" />
 <space x="712" y="237" dx="-2" dy="15" />
 <space x="719" y="237" dx="-3" dy="15" />
 <space x="722" y="237" dx="-4" dy="15" />
 <space x="723" y="237" dx="-4" dy="15" />
 <space x="723" y="237" dx="-3" dy="15" />
 <box x="721" y="237" dx="12" dy="15" value="\" numac="2" weights="98,86" achars="\,1" />
</line>
<line x="478" y="247" dx="271" dy="28" value="10">
 <space x="478" y="257" dx="-4" dy="15" />
 <space x="475" y="257" dx="-4" dy="15" />
 <space x="473" y="257" dx="-4" dy="15" />
 <space x="472" y="257" dx="-4" dy="15" />
 <space x="471" y="257" dx="-3" dy="15" />
 <space x="472" y="257" dx="-4" dy="15" />
 <space x="472" y="257" dx="-3" dy="15" />
 <space x="474" y="257" dx="-4" dy="15" />
 <space x="475" y="257" dx="-4" dy="15" />
 <space x="476" y="257" dx="-4" dy="15" />
 <space x="477" y="257" dx="-4" dy="15" />
 <space x="477" y="257" dx="-3" dy="15" />
 <space x="478" y="257" dx="-4" dy="15" />
 <space x="478" y="257" dx="-3" dy="15" />
 <space x="479" y="257" dx="-4" dy="15" />
 <space x="479" y="257" dx="-4" dy="15" />
 <space x="479" y="257" dx="-3" dy="15" />
 <space x="480" y="257" dx="-4" dy="15" />
 <space x="480" y="257" dx="-4" dy="15" />
 <space x="480" y="257" dx="-4" dy="15" />
 <space x="480" y="257" dx="-3" dy="15" />
 <space x="481" y="257" dx="-4" dy="15" />
 <space x="478" y="257" dx="12" dy="15" />
 <box x="478" y="257" dx="12" dy="15" value="/" numac="2" weights="98,91" achars="/,l" />
 <space x="491" y="257" dx="16" dy="15" />
 <space x="527" y="257" dx="15" dy="15" />
 <space x="575" y="257" dx="13" dy="15" />
 <space x="626" y="257" dx="9" dy="15" />
 <space x="670" y="257" dx="5" dy="15" />
 <space x="702" y="257" dx="2" dy="15" />
 <space x="722" y="257" dx="-1" dy="15" />
 <space x="732" y="257" dx="-2" dy="15" />
 <space x="737" y="257" dx="-4" dy="15" />
 <space x="738" y="257" dx="-3" dy="15" />
 <space x="739" y="257" dx="-4" dy="15" />
 <space x="739" y="257" dx="-3" dy="15" />
 <box x="737" y="257" dx="12" dy="15" value="\" numac="1" weights="98" achars="\" />
</line>
<line x="463" y="276" dx="302" dy="17" value="11">
 <space x="463" y="278" dx="-4" dy="15" />
 <space x="460" y="278" dx="-4" dy="15" />
 <space x="458" y="278" dx="-4" dy="15" />
 <space x="457" y="278" dx="-4" dy="15" />
 <space x="456" y="278" dx="-3" dy="15" />
 <space x="457" y="278" dx="-3" dy="15" />
 <space x="458" y="278" dx="-3" dy="15" />
 <space x="459" y="278" dx="-3" dy="15" />
 <space x="460" y="278" dx="-3" dy="15" />
 <space x="461" y="278" dx="-3" dy="15" />
 <space x="462" y="278" dx="-3" dy="15" />
 <space x="463" y="278" dx="-4" dy="15" />
 <space x="463" y="278" dx="-3" dy="15" />
 <space x="464" y="278" dx="-4" dy="15" />
 <space x="464" y="278" dx="-4" dy="15" />
 <space x="464" y="278" dx="-3" dy="15" />
 <space x="465" y="278" dx="-4" dy="15" />
 <space x="465" y="278" dx="-4" dy="15" />
 <space x="465" y="278" dx="-4" dy="15" />
 <space x="465" y="278" dx="-3" dy="15" />
 <space x="466" y="278" dx="-4" dy="15" />
 <space x="463" y="278" dx="12" dy="15" />
 <box x="463" y="278" dx="12" dy="15" value="/" numac="2" weights="98,97" achars="/,r" />
 <space x="476" y="280" dx="16" dy="15" />
 <space x="511" y="280" dx="15" dy="15" />
 <space x="556" y="280" dx="11" dy="15" />
 <space x="598" y="280" dx="6" dy="15" />
 <space x="629" y="280" dx="2" dy="15" />
 <space x="647" y="280" dx="-1" dy="15" />
 <space x="655" y="280" dx="-2" dy="15" />
 <space x="658" y="280" dx="-3" dy="15" />
 <space x="659" y="280" dx="-3" dy="15" />
 <box x="657" y="280" dx="15" dy="15" value="_" numac="1" weights="94" achars="f" />
 <space x="673" y="278" dx="16" dy="15" />
 <space x="706" y="278" dx="12" dy="15" />
 <space x="737" y="278" dx="5" dy="15" />
 <space x="752" y="278" dx="-1" dy="15" />
 <box x="752" y="278" dx="13" dy="15" value="\" numac="2" weights="100,87" achars="\,1" />
</line>
<line x="447" y="288" dx="333" dy="28" value="12">
 <space x="447" y="298" dx="-4" dy="15" />
 <space x="444" y="298" dx="-4" dy="15" />
 <space x="442" y="298" dx="-4" dy="15" />
 <space x="441" y="298" dx="-4" dy="15" />
 <space x="440" y="298" dx="-3" dy="15" />
 <space x="441" y="298" dx="-3" dy="15" />
 <space x="442" y="298" dx="-3" dy="15" />
 <space x="443" y="298" dx="-3" dy="15" />
 <space x="444" y="298" dx="-3" dy="15" />
 <space x="445" y="298" dx="-3" dy="15" />
 <space x="446" y="298" dx="-3" dy="15" />
 <space x="447" y="298" dx="-4" dy="15" />
 <space x="447" y="298" dx="-3" dy="15" />
 <space x="448" y="298" dx="-4" dy="15" />
 <space x="448" y="298" dx="-4" dy="15" />
 <space x="448" y="298" dx="-3" dy="15" />
 <space x="449" y="298" dx="-4" dy="15" />
 <space x="449" y="298" dx="-4" dy="15" />
 <space x="449" y="298" dx="-4" dy="15" />
 <space x="449" y="298" dx="-3" dy="15" />
 <space x="450" y="298" dx="-4" dy="15" />
 <space x="447" y="298" dx="12" dy="15" />
 <box x="447" y="298" dx="12" dy="15" value="/" numac="1" weights="98" achars="/" />
 <space x="460" y="298" dx="16" dy="15" />
 <space x="496" y="298" dx="16" dy="15" />
 <space x="547" y="298" dx="13" dy="15" />
 <space x="603" y="298" dx="10" dy="15" />
 <space x="655" y="298" dx="7" dy="15" />
 <space x="699" y="298" dx="3" dy="15" />
 <space x="730" y="298" dx="0" dy="15" />
 <space x="749" y="298" dx="-1" dy="15" />
 <space x="760" y="298" dx="-2" dy="15" />
 <space x="766" y="298" dx="-3" dy="15" />
 <space x="768" y="298" dx="-3" dy="15" />
 <space x="769" y="298" dx="-3" dy="15" />
 <space x="770" y="298" dx="-4" dy="15" />
 <space x="770" y="298" dx="-4" dy="15" />
 <space x="770" y="298" dx="-3" dy="15" />
 <box x="768" y="298" dx="12" dy="15" value="\" numac="1" weights="98" achars="\" />
</line>
<line x="71" y="309" dx="725" dy="28" value="13">
 <space x="74" y="317" dx="-1" dy="16" />
 <space x="71" y="317" dx="20" dy="16" />
 <box x="71" y="317" dx="20" dy="16" value="q" numac="1" weights="95" achars="q" />
 <box x="87" y="333" dx="4" dy="4" value="." numac="2" weights="99,96" achars=".,," />
 <space x="92" y="319" dx="16" dy="15" />
 <space x="128" y="319" dx="15" dy="15" />
 <space x="178" y="319" dx="13" dy="15" />
 <space x="234" y="319" dx="10" dy="15" />
 <space x="289" y="319" dx="7" dy="15" />
 <space x="337" y="319" dx="4" dy="15" />
 <space x="374" y="319" dx="1" dy="15" />
 <space x="399" y="319" dx="0" dy="15" />
 <space x="416" y="319" dx="-2" dy="15" />
 <space x="425" y="319" dx="-3" dy="15" />
 <space x="429" y="319" dx="-3" dy="15" />
 <space x="431" y="319" dx="-4" dy="15" />
 <space x="432" y="319" dx="-4" dy="15" />
 <space x="432" y="319" dx="-3" dy="15" />
 <space x="433" y="319" dx="-4" dy="15" />
 <space x="433" y="319" dx="-4" dy="15" />
 <space x="433" y="319" dx="-3" dy="15" />
 <box x="431" y="319" dx="13" dy="15" value="/" numac="2" weights="98,91" achars="/,l" />
 <space x="445" y="308" dx="17" dy="16" />
 <space x="481" y="308" dx="15" dy="16" />
 <space x="525" y="308" dx="10" dy="16" />
 <space x="561" y="308" dx="4" dy="16" />
 <space x="582" y="308" dx="0" dy="16" />
 <space x="591" y="308" dx="-2" dy="16" />
 <space x="594" y="308" dx="-3" dy="16" />
 <box x="592" y="308" dx="16" dy="16" value="_" />
 <space x="609" y="319" dx="18" dy="15" />
 <space x="647" y="319" dx="16" dy="15" />
 <space x="694" y="319" dx="11" dy="15" />
 <space x="736" y="319" dx="6" dy="15" />
 <space x="764" y="319" dx="1" dy="15" />
 <space x="778" y="319" dx="-1" dy="15" />
 <space x="784" y="319" dx="-3" dy="15" />
 <space x="785" y="319" dx="-3" dy="15" />
 <box x="783" y="319" dx="13" dy="15" value="\" numac="1" weights="98" achars="\" />
</line>
<line x="37" y="330" dx="774" dy="28" value="14">
 <space x="37" y="353" dx="25" dy="6" />
 <box x="37" y="353" dx="25" dy="6" value="n" numac="1" weights="96" achars="n" />
 <space x="63" y="340" dx="15" dy="15" />
 <space x="97" y="340" dx="15" dy="15" />
 <space x="147" y="340" dx="13" dy="15" />
 <space x="204" y="340" dx="10" dy="15" />
 <space x="260" y="340" dx="7" dy="15" />
 <space x="309" y="340" dx="5" dy="15" />
 <space x="349" y="340" dx="2" dy="15" />
 <space x="378" y="340" dx="-1" dy="15" />
 <space x="396" y="340" dx="-2" dy="15" />
 <space x="407" y="340" dx="-3" dy="15" />
 <space x="412" y="340" dx="-3" dy="15" />
 <space x="415" y="340" dx="-3" dy="15" />
 <space x="417" y="340" dx="-4" dy="15" />
 <space x="417" y="340" dx="-4" dy="15" />
 <space x="417" y="340" dx="-3" dy="15" />
 <space x="418" y="340" dx="-4" dy="15" />
 <space x="418" y="340" dx="-4" dy="15" />
 <space x="418" y="340" dx="-3" dy="15" />
 <box x="416" y="340" dx="12" dy="15" value="/" numac="2" weights="98,97" achars="/,r" />
 <space x="429" y="340" dx="15" dy="15" />
 <space x="463" y="340" dx="15" dy="15" />
 <space x="513" y="340" dx="13" dy="15" />
 <space x="570" y="340" dx="10" dy="15" />
 <space x="627" y="340" dx="8" dy="15" />
 <space x="679" y="340" dx="5" dy="15" />
 <space x="721" y="340" dx="3" dy="15" />
 <space x="753" y="340" dx="0" dy="15" />
 <space x="774" y="340" dx="-2" dy="15" />
 <space x="786" y="340" dx="-2" dy="15" />
 <space x="793" y="340" dx="-3" dy="15" />
 <space x="797" y="340" dx="-4" dy="15" />
 <space x="799" y="340" dx="-4" dy="15" />
 <space x="800" y="340" dx="-4" dy="15" />
 <space x="800" y="340" dx="-4" dy="15" />
 <space x="800" y="340" dx="-3" dy="15" />
 <space x="801" y="340" dx="-4" dy="15" />
 <space x="801" y="340" dx="-4" dy="15" />
 <space x="801" y="340" dx="-3" dy="15" />
 <box x="799" y="340" dx="12" dy="15" value="\" numac="1" weights="98" achars="\" />
</line>
<line x="37" y="358" dx="790" dy="18" value="15">
 <space x="37" y="361" dx="21" dy="13" />
 <box x="37" y="361" dx="21" dy="13" value="_" />
 <space x="59" y="360" dx="16" dy="15" />
 <space x="95" y="360" dx="15" dy="15" />
 <space x="145" y="360" dx="13" dy="15" />
 <space x="202" y="360" dx="10" dy="15" />
 <space x="257" y="360" dx="7" dy="15" />
 <space x="305" y="360" dx="4" dy="15" />
 <space x="342" y="360" dx="2" dy="15" />
 <space x="368" y="360" dx="0" dy="15" />
 <space x="385" y="360" dx="-2" dy="15" />
 <space x="394" y="360" dx="-3" dy="15" />
 <space x="398" y="360" dx="-3" dy="15" />
 <space x="400" y="360" dx="-4" dy="15" />
 <space x="401" y="360" dx="-4" dy="15" />
 <space x="401" y="360" dx="-3" dy="15" />
 <space x="402" y="360" dx="-4" dy="15" />
 <space x="402" y="360" dx="-4" dy="15" />
 <space x="402" y="360" dx="-3" dy="15" />
 <box x="400" y="360" dx="13" dy="15" value="/" numac="1" weights="100" achars="/" />
 <space x="414" y="360" dx="16" dy="15" />
 <space x="450" y="360" dx="15" dy="15" />
 <space x="501" y="360" dx="13" dy="15" />
 <space x="560" y="360" dx="11" dy="15" />
 <space x="621" y="360" dx="8" dy="15" />
 <space x="676" y="360" dx="6" dy="15" />
 <space x="723" y="360" dx="2" dy="15" />
 <space x="757" y="360" dx="1" dy="15" />
 <space x="782" y="360" dx="-1" dy="15" />
 <space x="797" y="360" dx="-2" dy="15" />
 <space x="806" y="360" dx="-3" dy="15" />
 <space x="811" y="360" dx="-4" dy="15" />
 <space x="813" y="360" dx="-4" dy="15" />
 <space x="814" y="360" dx="-4" dy="15" />
 <space x="815" y="360" dx="-4" dy="15" />
 <space x="815" y="360" dx="-3" dy="15" />
 <space x="816" y="360" dx="-4" dy="15" />
 <space x="816" y="360" dx="-4" dy="15" />
 <space x="816" y="360" dx="-4" dy="15" />
 <space x="816" y="360" dx="-3" dy="15" />
 <box x="814" y="360" dx="13" dy="15" value="\" numac="1" weights="100" achars="\" />
</line>
<line x="37" y="377" dx="805" dy="17" value="16">
 <space x="37" y="377" dx="21" dy="13" />
 <box x="37" y="377" dx="21" dy="13" value="_" />
 <space x="59" y="381" dx="16" dy="15" />
 <space x="95" y="381" dx="16" dy="15" />
 <space x="146" y="381" dx="13" dy="15" />
 <space x="202" y="381" dx="11" dy="15" />
 <space x="257" y="381" dx="7" dy="15" />
 <space x="303" y="381" dx="4" dy="15" />
 <space x="338" y="381" dx="1" dy="15" />
 <space x="361" y="381" dx="-1" dy="15" />
 <space x="374" y="381" dx="-2" dy="15" />
 <space x="381" y="381" dx="-3" dy="15" />
 <space x="384" y="381" dx="-3" dy="15" />
 <space x="386" y="381" dx="-4" dy="15" />
 <space x="386" y="381" dx="-3" dy="15" />
 <space x="387" y="381" dx="-4" dy="15" />
 <space x="387" y="381" dx="-4" dy="15" />
 <space x="387" y="381" dx="-3" dy="15" />
 <box x="385" y="381" dx="12" dy="15" value="/" numac="2" weights="97,94" achars="/,r" />
 <space x="398" y="381" dx="15" dy="15" />
 <space x="433" y="381" dx="15" dy="15" />
 <space x="483" y="381" dx="14" dy="15" />
 <space x="543" y="381" dx="11" dy="15" />
 <space x="605" y="381" dx="9" dy="15" />
 <space x="664" y="381" dx="6" dy="15" />
 <space x="715" y="381" dx="3" dy="15" />
 <space x="755" y="381" dx="1" dy="15" />
 <space x="784" y="381" dx="0" dy="15" />
 <space x="804" y="381" dx="-2" dy="15" />
 <space x="816" y="381" dx="-2" dy="15" />
 <space x="824" y="381" dx="-4" dy="15" />
 <space x="827" y="381" dx="-3" dy="15" />
 <space x="829" y="381" dx="-3" dy="15" />
 <space x="830" y="381" dx="-3" dy="15" />
 <space x="831" y="381" dx="-4" dy="15" />
 <space x="831" y="381" dx="-4" dy="15" />
 <space x="831" y="381" dx="-3" dy="15" />
 <space x="832" y="381" dx="-4" dy="15" />
 <space x="832" y="381" dx="-4" dy="15" />
 <space x="832" y="381" dx="-4" dy="15" />
 <space x="832" y="381" dx="-3" dy="15" />
 <box x="830" y="381" dx="12" dy="15" value="\" numac="1" weights="97" achars="\" />
</line>
<line x="43" y="394" dx="815" dy="20" value="17">
 <space x="43" y="394" dx="21" dy="14" />
 <box x="43" y="394" dx="21" dy="14" value="_" />
 <space x="65" y="401" dx="16" dy="15" />
 <space x="101" y="401" dx="15" dy="15" />
 <space x="151" y="401" dx="13" dy="15" />
 <space x="206" y="401" dx="10" dy="15" />
 <space x="258" y="401" dx="6" dy="15" />
 <space x="300" y="401" dx="3" dy="15" />
 <space x="331" y="401" dx="0" dy="15" />
 <space x="350" y="401" dx="-1" dy="15" />
 <space x="361" y="401" dx="-2" dy="15" />
 <space x="367" y="401" dx="-3" dy="15" />
 <space x="369" y="401" dx="-3" dy="15" />
 <space x="370" y="401" dx="-3" dy="15" />
 <space x="371" y="401" dx="-4" dy="15" />
 <space x="371" y="401" dx="-4" dy="15" />
 <space x="371" y="401" dx="-3" dy="15" />
 <box x="369" y="401" dx="12" dy="15" value="/" numac="1" weights="97" achars="/" />
 <space x="382" y="401" dx="16" dy="15" />
 <space x="418" y="401" dx="16" dy="15" />
 <space x="471" y="401" dx="14" dy="15" />
 <space x="533" y="401" dx="12" dy="15" />
 <space x="598" y="401" dx="9" dy="15" />
 <space x="660" y="401" dx="6" dy="15" />
 <space x="714" y="401" dx="4" dy="15" />
 <space x="758" y="401" dx="2" dy="15" />
 <space x="791" y="401" dx="0" dy="15" />
 <space x="814" y="401" dx="-2" dy="15" />
 <space x="828" y="401" dx="-2" dy="15" />
 <space x="837" y="401" dx="-3" dy="15" />
 <space x="842" y="401" dx="-4" dy="15" />
 <space x="844" y="401" dx="-3" dy="15" />
 <space x="846" y="401" dx="-4" dy="15" />
 <space x="846" y="401" dx="-3" dy="15" />
 <space x="847" y="401" dx="-4" dy="15" />
 <space x="847" y="401" dx="-4" dy="15" />
 <space x="847" y="401" dx="-3" dy="15" />
 <space x="848" y="401" dx="-4" dy="15" />
 <space x="848" y="401" dx="-4" dy="15" />
 <space x="848" y="401" dx="-4" dy="15" />
 <space x="848" y="401" dx="-3" dy="15" />
 <box x="846" y="401" dx="12" dy="15" value="\" numac="1" weights="97" achars="\" />
</line>
<line x="37" y="412" dx="836" dy="28" value="18">
 <space x="37" y="410" dx="21" dy="20" />
 <box x="37" y="410" dx="21" dy="20" value="%" numac="2" weights="100,88" achars="%,g" />
 <box x="37" y="433" dx="25" dy="6" value="v" numac="2" weights="98,94" achars="v,y" />
 <space x="63" y="422" dx="17" dy="15" />
 <space x="100" y="422" dx="16" dy="15" />
 <space x="151" y="422" dx="13" dy="15" />
 <space x="206" y="422" dx="9" dy="15" />
 <space x="256" y="422" dx="6" dy="15" />
 <space x="296" y="422" dx="3" dy="15" />
 <space x="324" y="422" dx="0" dy="15" />
 <space x="341" y="422" dx="-2" dy="15" />
 <space x="349" y="422" dx="-3" dy="15" />
 <space x="353" y="422" dx="-3" dy="15" />
 <space x="355" y="422" dx="-4" dy="15" />
 <space x="355" y="422" dx="-3" dy="15" />
 <space x="356" y="422" dx="-4" dy="15" />
 <space x="356" y="422" dx="-3" dy="15" />
 <box x="354" y="422" dx="12" dy="15" value="/" numac="2" weights="98,97" achars="/,r" />
 <space x="367" y="422" dx="15" dy="15" />
 <space x="402" y="422" dx="15" dy="15" />
 <space x="453" y="422" dx="14" dy="15" />
 <space x="515" y="422" dx="12" dy="15" />
 <space x="581" y="422" dx="10" dy="15" />
 <space x="646" y="422" dx="7" dy="15" />
 <space x="704" y="422" dx="4" dy="15" />
 <space x="752" y="422" dx="2" dy="15" />
 <space x="789" y="422" dx="1" dy="15" />
 <space x="817" y="422" dx="-1" dy="15" />
 <space x="835" y="422" dx="-2" dy="15" />
 <space x="847" y="422" dx="-3" dy="15" />
 <space x="854" y="422" dx="-4" dy="15" />
 <space x="857" y="422" dx="-3" dy="15" />
 <space x="860" y="422" dx="-4" dy="15" />
 <space x="861" y="422" dx="-4" dy="15" />
 <space x="861" y="422" dx="-3" dy="15" />
 <space x="862" y="422" dx="-4" dy="15" />
 <space x="862" y="422" dx="-4" dy="15" />
 <space x="862" y="422" dx="-3" dy="15" />
 <space x="863" y="422" dx="-4" dy="15" />
 <space x="863" y="422" dx="-4" dy="15" />
 <space x="863" y="422" dx="-4" dy="15" />
 <space x="863" y="422" dx="-4" dy="15" />
 <space x="863" y="422" dx="-3" dy="15" />
 <box x="861" y="422" dx="12" dy="15" value="\" numac="1" weights="98" achars="\" />
</line>
<line x="43" y="432" dx="846" dy="28" value="19">
 <space x="43" y="441" dx="15" dy="14" />
 <box x="43" y="441" dx="15" dy="14" value="_" />
 <box x="43" y="456" dx="15" dy="10" value="n" numac="2" weights="96,87" achars="n,4" />
 <box x="71" y="435" dx="20" dy="19" value="%" numac="1" weights="100" achars="%" />
 <space x="92" y="442" dx="27" dy="15" />
 <space x="147" y="442" dx="24" dy="15" />
 <space x="214" y="442" dx="17" dy="15" />
 <space x="272" y="442" dx="10" dy="15" />
 <space x="312" y="442" dx="3" dy="15" />
 <space x="331" y="442" dx="-1" dy="15" />
 <space x="338" y="442" dx="-3" dy="15" />
 <space x="340" y="442" dx="-3" dy="15" />
 <box x="338" y="442" dx="12" dy="15" value="/" numac="1" weights="98" achars="/" />
 <space x="351" y="442" dx="25" dy="15" />
 <space x="404" y="442" dx="24" dy="15" />
 <space x="479" y="442" dx="21" dy="15" />
 <space x="564" y="442" dx="17" dy="15" />
 <space x="648" y="442" dx="12" dy="15" />
 <space x="721" y="442" dx="9" dy="15" />
 <space x="780" y="442" dx="4" dy="15" />
 <space x="821" y="442" dx="2" dy="15" />
 <space x="848" y="442" dx="0" dy="15" />
 <space x="864" y="442" dx="-2" dy="15" />
 <space x="872" y="442" dx="-3" dy="15" />
 <space x="876" y="442" dx="-4" dy="15" />
 <space x="877" y="442" dx="-3" dy="15" />
 <space x="878" y="442" dx="-4" dy="15" />
 <space x="878" y="442" dx="-3" dy="15" />
 <space x="879" y="442" dx="-4" dy="15" />
 <space x="879" y="442" dx="-4" dy="15" />
 <space x="879" y="442" dx="-3" dy="15" />
 <box x="877" y="442" dx="12" dy="15" value="\" numac="1" weights="98" achars="\" />
</line>
<line x="323" y="453" dx="581" dy="28" value="20">
 <space x="323" y="463" dx="-4" dy="15" />
 <space x="320" y="463" dx="-3" dy="15" />
 <space x="319" y="463" dx="-3" dy="15" />
 <space x="319" y="463" dx="-3" dy="15" />
 <space x="320" y="463" dx="-4" dy="15" />
 <space x="320" y="463" dx="-3" dy="15" />
 <space x="322" y="463" dx="-4" dy="15" />
 <space x="323" y="463" dx="-4" dy="15" />
 <space x="323" y="463" dx="-3" dy="15" />
 <space x="324" y="463" dx="-4" dy="15" />
 <space x="324" y="463" dx="-3" dy="15" />
 <space x="325" y="463" dx="-4" dy="15" />
 <space x="325" y="463" dx="-3" dy="15" />
 <space x="326" y="463" dx="-4" dy="15" />
 <space x="323" y="463" dx="12" dy="15" />
 <box x="323" y="463" dx="12" dy="15" value="/" numac="2" weights="98,97" achars="/,r" />
 <space x="336" y="463" dx="15" dy="15" />
 <space x="371" y="463" dx="15" dy="15" />
 <space x="423" y="463" dx="14" dy="15" />
 <space x="486" y="463" dx="13" dy="15" />
 <space x="556" y="463" dx="10" dy="15" />
 <space x="625" y="463" dx="8" dy="15" />
 <space x="689" y="463" dx="6" dy="15" />
 <space x="745" y="463" dx="3" dy="15" />
 <space x="790" y="463" dx="1" dy="15" />
 <space x="825" y="463" dx="-1" dy="15" />
 <space x="850" y="463" dx="-2" dy="15" />
 <space x="867" y="463" dx="-3" dy="15" />
 <space x="877" y="463" dx="-3" dy="15" />
 <space x="884" y="463" dx="-3" dy="15" />
 <space x="888" y="463" dx="-4" dy="15" />
 <space x="890" y="463" dx="-4" dy="15" />
 <space x="891" y="463" dx="-4" dy="15" />
 <space x="892" y="463" dx="-4" dy="15" />
 <space x="892" y="463" dx="-3" dy="15" />
 <space x="893" y="463" dx="-4" dy="15" />
 <space x="893" y="463" dx="-4" dy="15" />
 <space x="893" y="463" dx="-4" dy="15" />
 <space x="893" y="463" dx="-3" dy="15" />
 <space x="894" y="463" dx="-4" dy="15" />
 <space x="894" y="463" dx="-4" dy="15" />
 <space x="894" y="463" dx="-4" dy="15" />
 <space x="894" y="463" dx="-4" dy="15" />
 <space x="894" y="463" dx="-3" dy="15" />
 <box x="892" y="463" dx="12" dy="15" value="\" numac="1" weights="98" achars="\" />
</line>
<line x="307" y="481" dx="613" dy="17" value="21">
 <space x="307" y="483" dx="-4" dy="15" />
 <space x="304" y="483" dx="-3" dy="15" />
 <space x="303" y="483" dx="-3" dy="15" />
 <space x="303" y="483" dx="-3" dy="15" />
 <space x="304" y="483" dx="-3" dy="15" />
 <space x="305" y="483" dx="-3" dy="15" />
 <space x="306" y="483" dx="-3" dy="15" />
 <space x="307" y="483" dx="-3" dy="15" />
 <space x="308" y="483" dx="-4" dy="15" />
 <space x="308" y="483" dx="-3" dy="15" />
 <space x="309" y="483" dx="-4" dy="15" />
 <space x="309" y="483" dx="-3" dy="15" />
 <space x="310" y="483" dx="-4" dy="15" />
 <space x="307" y="483" dx="12" dy="15" />
 <box x="307" y="483" dx="12" dy="15" value="/" numac="1" weights="97" achars="/" />
 <space x="320" y="483" dx="15" dy="15" />
 <space x="355" y="483" dx="15" dy="15" />
 <space x="407" y="483" dx="14" dy="15" />
 <space x="470" y="483" dx="13" dy="15" />
 <space x="540" y="483" dx="11" dy="15" />
 <space x="611" y="483" dx="8" dy="15" />
 <space x="678" y="483" dx="5" dy="15" />
 <space x="736" y="483" dx="4" dy="15" />
 <space x="786" y="483" dx="2" dy="15" />
 <space x="825" y="483" dx="0" dy="15" />
 <space x="854" y="483" dx="-1" dy="15" />
 <space x="874" y="483" dx="-2" dy="15" />
 <space x="888" y="483" dx="-3" dy="15" />
 <space x="896" y="483" dx="-3" dy="15" />
 <space x="901" y="483" dx="-3" dy="15" />
 <space x="905" y="483" dx="-4" dy="15" />
 <space x="906" y="483" dx="-3" dy="15" />
 <space x="907" y="483" dx="-3" dy="15" />
 <space x="908" y="483" dx="-4" dy="15" />
 <space x="908" y="483" dx="-3" dy="15" />
 <space x="909" y="483" dx="-4" dy="15" />
 <space x="909" y="483" dx="-4" dy="15" />
 <space x="909" y="483" dx="-4" dy="15" />
 <space x="909" y="483" dx="-3" dy="15" />
 <space x="910" y="483" dx="-4" dy="15" />
 <space x="910" y="483" dx="-4" dy="15" />
 <space x="910" y="483" dx="-4" dy="15" />
 <space x="910" y="483" dx="-4" dy="15" />
 <space x="910" y="483" dx="-4" dy="15" />
 <space x="910" y="483" dx="-3" dy="15" />
 <box x="908" y="483" dx="12" dy="15" value="\" numac="1" weights="100" achars="\" />
</line>
<line x="292" y="502" dx="643" dy="17" value="22">
 <space x="292" y="504" dx="-4" dy="15" />
 <space x="289" y="504" dx="-3" dy="15" />
 <space x="288" y="504" dx="-3" dy="15" />
 <space x="288" y="504" dx="-3" dy="15" />
 <space x="289" y="504" dx="-3" dy="15" />
 <space x="290" y="504" dx="-3" dy="15" />
 <space x="291" y="504" dx="-3" dy="15" />
 <space x="292" y="504" dx="-3" dy="15" />
 <space x="293" y="504" dx="-4" dy="15" />
 <space x="293" y="504" dx="-3" dy="15" />
 <space x="294" y="504" dx="-4" dy="15" />
 <space x="294" y="504" dx="-3" dy="15" />
 <space x="295" y="504" dx="-4" dy="15" />
 <space x="292" y="504" dx="12" dy="15" />
 <box x="292" y="504" dx="12" dy="15" value="/" numac="2" weights="97,94" achars="/,r" />
 <space x="305" y="504" dx="16" dy="15" />
 <space x="341" y="504" dx="15" dy="15" />
 <space x="393" y="504" dx="15" dy="15" />
 <space x="459" y="504" dx="12" dy="15" />
 <space x="530" y="504" dx="11" dy="15" />
 <space x="603" y="504" dx="9" dy="15" />
 <space x="673" y="504" dx="6" dy="15" />
 <space x="735" y="504" dx="4" dy="15" />
 <space x="788" y="504" dx="2" dy="15" />
 <space x="830" y="504" dx="0" dy="15" />
 <space x="861" y="504" dx="-1" dy="15" />
 <space x="884" y="504" dx="-2" dy="15" />
 <space x="899" y="504" dx="-2" dy="15" />
 <space x="909" y="504" dx="-3" dy="15" />
 <space x="915" y="504" dx="-3" dy="15" />
 <space x="919" y="504" dx="-4" dy="15" />
 <space x="921" y="504" dx="-4" dy="15" />
 <space x="922" y="504" dx="-4" dy="15" />
 <space x="923" y="504" dx="-4" dy="15" />
 <space x="923" y="504" dx="-4" dy="15" />
 <space x="923" y="504" dx="-3" dy="15" />
 <space x="924" y="504" dx="-4" dy="15" />
 <space x="924" y="504" dx="-4" dy="15" />
 <space x="924" y="504" dx="-4" dy="15" />
 <space x="924" y="504" dx="-3" dy="15" />
 <space x="925" y="504" dx="-4" dy="15" />
 <space x="925" y="504" dx="-4" dy="15" />
 <space x="925" y="504" dx="-4" dy="15" />
 <space x="925" y="504" dx="-4" dy="15" />
 <space x="925" y="504" dx="-4" dy="15" />
 <space x="925" y="504" dx="-3" dy="15" />
 <box x="923" y="504" dx="12" dy="15" value="\" numac="1" weights="100" achars="\" />
</line>
<line x="276" y="522" dx="675" dy="17" value="23">
 <space x="276" y="524" dx="-4" dy="15" />
 <space x="274" y="524" dx="-4" dy="15" />
 <space x="273" y="524" dx="-4" dy="15" />
 <space x="273" y="524" dx="-4" dy="15" />
 <space x="273" y="524" dx="-3" dy="15" />
 <space x="275" y="524" dx="-4" dy="15" />
 <space x="276" y="524" dx="-4" dy="15" />
 <space x="277" y="524" dx="-4" dy="15" />
 <space x="277" y="524" dx="-3" dy="15" />
 <space x="278" y="524" dx="-4" dy="15" />
 <space x="278" y="524" dx="-3" dy="15" />
 <space x="279" y="524" dx="-4" dy="15" />
 <space x="276" y="524" dx="12" dy="15" />
 <box x="276" y="524" dx="12" dy="15" value="/" numac="1" weights="97" achars="/" />
 <space x="289" y="524" dx="15" dy="15" />
 <space x="324" y="524" dx="15" dy="15" />
 <space x="376" y="524" dx="14" dy="15" />
 <space x="441" y="524" dx="12" dy="15" />
 <space x="513" y="524" dx="10" dy="15" />
 <space x="587" y="524" dx="9" dy="15" />
 <space x="659" y="524" dx="7" dy="15" />
 <space x="725" y="524" dx="4" dy="15" />
 <space x="781" y="524" dx="2" dy="15" />
 <space x="827" y="524" dx="0" dy="15" />
 <space x="862" y="524" dx="0" dy="15" />
 <space x="889" y="524" dx="-2" dy="15" />
 <space x="907" y="524" dx="-2" dy="15" />
 <space x="920" y="524" dx="-3" dy="15" />
 <space x="928" y="524" dx="-4" dy="15" />
 <space x="932" y="524" dx="-3" dy="15" />
 <space x="935" y="524" dx="-3" dy="15" />
 <space x="937" y="524" dx="-4" dy="15" />
 <space x="938" y="524" dx="-4" dy="15" />
 <space x="939" y="524" dx="-4" dy="15" />
 <space x="939" y="524" dx="-4" dy="15" />
 <space x="939" y="524" dx="-3" dy="15" />
 <space x="940" y="524" dx="-4" dy="15" />
 <space x="940" y="524" dx="-4" dy="15" />
 <space x="940" y="524" dx="-4" dy="15" />
 <space x="940" y="524" dx="-4" dy="15" />
 <space x="940" y="524" dx="-3" dy="15" />
 <space x="941" y="524" dx="-4" dy="15" />
 <space x="941" y="524" dx="-4" dy="15" />
 <space x="941" y="524" dx="-4" dy="15" />
 <space x="941" y="524" dx="-4" dy="15" />
 <space x="941" y="524" dx="-4" dy="15" />
 <space x="941" y="524" dx="-3" dy="15" />
 <box x="939" y="524" dx="12" dy="15" value="\" numac="1" weights="100" achars="\" />
</line>
<line x="71" y="543" dx="895" dy="22" value="24">
 <space x="74" y="553" dx="-1" dy="13" />
 <space x="71" y="553" dx="20" dy="13" />
 <box x="71" y="553" dx="20" dy="13" value="_" />
 <space x="92" y="545" dx="17" dy="15" />
 <space x="129" y="545" dx="15" dy="15" />
 <space x="174" y="545" dx="11" dy="15" />
 <space x="215" y="545" dx="6" dy="15" />
 <space x="243" y="545" dx="1" dy="15" />
 <space x="256" y="545" dx="-1" dy="15" />
 <space x="262" y="545" dx="-3" dy="15" />
 <space x="263" y="545" dx="-3" dy="15" />
 <box x="261" y="545" dx="12" dy="15" value="/" numac="2" weights="100,93" achars="/,r" />
 <space x="274" y="544" dx="16" dy="16" />
 <space x="309" y="544" dx="15" dy="16" />
 <space x="356" y="544" dx="12" dy="16" />
 <space x="405" y="544" dx="8" dy="16" />
 <space x="447" y="544" dx="5" dy="16" />
 <space x="478" y="544" dx="2" dy="16" />
 <space x="498" y="544" dx="-2" dy="16" />
 <space x="507" y="544" dx="-2" dy="16" />
 <space x="512" y="544" dx="-4" dy="16" />
 <space x="513" y="544" dx="-3" dy="16" />
 <space x="514" y="544" dx="-4" dy="16" />
 <space x="514" y="544" dx="-3" dy="16" />
 <box x="512" y="544" dx="16" dy="16" value="_" />
 <space x="529" y="545" dx="16" dy="15" />
 <space x="565" y="545" dx="16" dy="15" />
 <space x="617" y="545" dx="14" dy="15" />
 <space x="678" y="545" dx="11" dy="15" />
 <space x="740" y="545" dx="9" dy="15" />
 <space x="799" y="545" dx="6" dy="15" />
 <space x="849" y="545" dx="3" dy="15" />
 <space x="887" y="545" dx="1" dy="15" />
 <space x="914" y="545" dx="0" dy="15" />
 <space x="933" y="545" dx="-2" dy="15" />
 <space x="943" y="545" dx="-2" dy="15" />
 <space x="949" y="545" dx="-3" dy="15" />
 <space x="952" y="545" dx="-3" dy="15" />
 <space x="954" y="545" dx="-4" dy="15" />
 <space x="955" y="545" dx="-4" dy="15" />
 <space x="955" y="545" dx="-4" dy="15" />
 <space x="955" y="545" dx="-3" dy="15" />
 <space x="956" y="545" dx="-4" dy="15" />
 <space x="956" y="545" dx="-4" dy="15" />
 <space x="956" y="545" dx="-4" dy="15" />
 <space x="956" y="545" dx="-3" dy="15" />
 <box x="954" y="545" dx="12" dy="15" value="\" numac="1" weights="100" achars="\" />
</line>
<line x="87" y="563" dx="895" dy="17" value="25">
 <space x="88" y="568" dx="-2" dy="4" />
 <space x="90" y="568" dx="-3" dy="4" />
 <space x="87" y="568" dx="4" dy="4" />
 <box x="87" y="568" dx="4" dy="4" value="&apos;" numac="1" weights="99" achars="&apos;" />
 <space x="92" y="566" dx="18" dy="15" />
 <space x="130" y="566" dx="16" dy="15" />
 <space x="175" y="566" dx="11" dy="15" />
 <space x="213" y="566" dx="4" dy="15" />
 <space x="235" y="566" dx="0" dy="15" />
 <space x="244" y="566" dx="-2" dy="15" />
 <space x="247" y="566" dx="-3" dy="15" />
 <box x="245" y="566" dx="12" dy="15" value="/" numac="1" weights="97" achars="/" />
 <space x="258" y="567" dx="15" dy="15" />
 <space x="292" y="567" dx="15" dy="15" />
 <space x="342" y="567" dx="13" dy="15" />
 <space x="399" y="567" dx="11" dy="15" />
 <space x="457" y="567" dx="8" dy="15" />
 <space x="509" y="567" dx="5" dy="15" />
 <space x="552" y="567" dx="2" dy="15" />
 <space x="583" y="567" dx="0" dy="15" />
 <space x="604" y="567" dx="-1" dy="15" />
 <space x="617" y="567" dx="-2" dy="15" />
 <space x="624" y="567" dx="-3" dy="15" />
 <space x="628" y="567" dx="-4" dy="15" />
 <space x="630" y="567" dx="-4" dy="15" />
 <space x="631" y="567" dx="-4" dy="15" />
 <space x="631" y="567" dx="-4" dy="15" />
 <space x="631" y="567" dx="-3" dy="15" />
 <space x="632" y="567" dx="-4" dy="15" />
 <space x="632" y="567" dx="-4" dy="15" />
 <space x="632" y="567" dx="-3" dy="15" />
 <box x="630" y="567" dx="16" dy="15" value="_" numac="1" weights="93" achars="f" />
 <space x="647" y="566" dx="16" dy="15" />
 <space x="683" y="566" dx="15" dy="15" />
 <space x="733" y="566" dx="13" dy="15" />
 <space x="789" y="566" dx="10" dy="15" />
 <space x="843" y="566" dx="7" dy="15" />
 <space x="889" y="566" dx="3" dy="15" />
 <space x="923" y="566" dx="1" dy="15" />
 <space x="946" y="566" dx="-1" dy="15" />
 <space x="959" y="566" dx="-2" dy="15" />
 <space x="966" y="566" dx="-3" dy="15" />
 <space x="969" y="566" dx="-3" dy="15" />
 <space x="971" y="566" dx="-4" dy="15" />
 <space x="971" y="566" dx="-3" dy="15" />
 <space x="972" y="566" dx="-4" dy="15" />
 <space x="972" y="566" dx="-4" dy="15" />
 <space x="972" y="566" dx="-3" dy="15" />
 <box x="970" y="566" dx="12" dy="15" value="\" numac="1" weights="100" achars="\" />
</line>
<line x="230" y="583" dx="767" dy="18" value="26">
 <space x="230" y="586" dx="-4" dy="16" />
 <space x="228" y="586" dx="-3" dy="16" />
 <space x="228" y="586" dx="-3" dy="16" />
 <space x="229" y="586" dx="-4" dy="16" />
 <space x="229" y="586" dx="-3" dy="16" />
 <space x="231" y="586" dx="-4" dy="16" />
 <space x="231" y="586" dx="-3" dy="16" />
 <space x="232" y="586" dx="-3" dy="16" />
 <space x="233" y="586" dx="-4" dy="16" />
 <space x="230" y="586" dx="12" dy="16" />
 <box x="230" y="586" dx="12" dy="16" value="/" numac="2" weights="97,94" achars="/,r" />
 <space x="243" y="586" dx="15" dy="15" />
 <space x="278" y="586" dx="15" dy="15" />
 <space x="330" y="586" dx="14" dy="15" />
 <space x="395" y="586" dx="13" dy="15" />
 <space x="469" y="586" dx="12" dy="15" />
 <space x="548" y="586" dx="9" dy="15" />
 <space x="625" y="586" dx="8" dy="15" />
 <space x="699" y="586" dx="5" dy="15" />
 <space x="764" y="586" dx="4" dy="15" />
 <space x="820" y="586" dx="2" dy="15" />
 <space x="866" y="586" dx="0" dy="15" />
 <space x="902" y="586" dx="-1" dy="15" />
 <space x="929" y="586" dx="-2" dy="15" />
 <space x="948" y="586" dx="-2" dy="15" />
 <space x="962" y="586" dx="-3" dy="15" />
 <space x="971" y="586" dx="-4" dy="15" />
 <space x="976" y="586" dx="-4" dy="15" />
 <space x="979" y="586" dx="-3" dy="15" />
 <space x="982" y="586" dx="-4" dy="15" />
 <space x="983" y="586" dx="-4" dy="15" />
 <space x="984" y="586" dx="-4" dy="15" />
 <space x="984" y="586" dx="-3" dy="15" />
 <space x="985" y="586" dx="-4" dy="15" />
 <space x="985" y="586" dx="-4" dy="15" />
 <space x="985" y="586" dx="-4" dy="15" />
 <space x="985" y="586" dx="-3" dy="15" />
 <space x="986" y="586" dx="-4" dy="15" />
 <space x="986" y="586" dx="-4" dy="15" />
 <space x="986" y="586" dx="-4" dy="15" />
 <space x="986" y="586" dx="-4" dy="15" />
 <space x="986" y="586" dx="-3" dy="15" />
 <space x="987" y="586" dx="-4" dy="15" />
 <space x="987" y="586" dx="-4" dy="15" />
 <space x="987" y="586" dx="-4" dy="15" />
 <space x="987" y="586" dx="-4" dy="15" />
 <space x="987" y="586" dx="-4" dy="15" />
 <space x="987" y="586" dx="-4" dy="15" />
 <space x="987" y="586" dx="-3" dy="15" />
 <box x="985" y="586" dx="12" dy="15" value="\" numac="1" weights="100" achars="\" />
</line>
<line x="214" y="604" dx="799" dy="17" value="27">
 <space x="214" y="607" dx="-4" dy="15" />
 <space x="212" y="607" dx="-3" dy="15" />
 <space x="212" y="607" dx="-3" dy="15" />
 <space x="213" y="607" dx="-4" dy="15" />
 <space x="213" y="607" dx="-3" dy="15" />
 <space x="215" y="607" dx="-4" dy="15" />
 <space x="215" y="607" dx="-3" dy="15" />
 <space x="216" y="607" dx="-3" dy="15" />
 <space x="217" y="607" dx="-4" dy="15" />
 <space x="214" y="607" dx="12" dy="15" />
 <box x="214" y="607" dx="12" dy="15" value="/" numac="1" weights="97" achars="/" />
 <space x="227" y="607" dx="15" dy="15" />
 <space x="262" y="607" dx="16" dy="15" />
 <space x="316" y="607" dx="14" dy="15" />
 <space x="382" y="607" dx="14" dy="15" />
 <space x="459" y="607" dx="11" dy="15" />
 <space x="539" y="607" dx="10" dy="15" />
 <space x="619" y="607" dx="8" dy="15" />
 <space x="695" y="607" dx="6" dy="15" />
 <space x="763" y="607" dx="4" dy="15" />
 <space x="822" y="607" dx="2" dy="15" />
 <space x="870" y="607" dx="1" dy="15" />
 <space x="909" y="607" dx="-1" dy="15" />
 <space x="938" y="607" dx="-2" dy="15" />
 <space x="959" y="607" dx="-2" dy="15" />
 <space x="974" y="607" dx="-3" dy="15" />
 <space x="984" y="607" dx="-3" dy="15" />
 <space x="991" y="607" dx="-4" dy="15" />
 <space x="994" y="607" dx="-3" dy="15" />
 <space x="997" y="607" dx="-4" dy="15" />
 <space x="998" y="607" dx="-3" dy="15" />
 <space x="1000" y="607" dx="-4" dy="15" />
 <space x="1000" y="607" dx="-4" dy="15" />
 <space x="1000" y="607" dx="-3" dy="15" />
 <space x="1001" y="607" dx="-4" dy="15" />
 <space x="1001" y="607" dx="-4" dy="15" />
 <space x="1001" y="607" dx="-3" dy="15" />
 <space x="1002" y="607" dx="-4" dy="15" />
 <space x="1002" y="607" dx="-4" dy="15" />
 <space x="1002" y="607" dx="-4" dy="15" />
 <space x="1002" y="607" dx="-4" dy="15" />
 <space x="1002" y="607" dx="-4" dy="15" />
 <space x="1002" y="607" dx="-3" dy="15" />
 <space x="1003" y="607" dx="-4" dy="15" />
 <space x="1003" y="607" dx="-4" dy="15" />
 <space x="1003" y="607" dx="-4" dy="15" />
 <space x="1003" y="607" dx="-4" dy="15" />
 <space x="1003" y="607" dx="-4" dy="15" />
 <space x="1003" y="607" dx="-4" dy="15" />
 <space x="1003" y="607" dx="-3" dy="15" />
 <box x="1001" y="607" dx="12" dy="15" value="\" numac="1" weights="100" achars="\" />
</line>
<line x="199" y="624" dx="829" dy="18" value="28">
 <space x="199" y="627" dx="-4" dy="16" />
 <space x="197" y="627" dx="-3" dy="16" />
 <space x="197" y="627" dx="-3" dy="16" />
 <space x="198" y="627" dx="-3" dy="16" />
 <space x="199" y="627" dx="-3" dy="16" />
 <space x="200" y="627" dx="-3" dy="16" />
 <space x="201" y="627" dx="-3" dy="16" />
 <space x="202" y="627" dx="-4" dy="16" />
 <space x="199" y="627" dx="12" dy="16" />
 <box x="199" y="627" dx="12" dy="16" value="/" numac="2" weights="97,94" achars="/,r" />
 <space x="212" y="627" dx="15" dy="15" />
 <space x="247" y="627" dx="15" dy="15" />
 <space x="299" y="627" dx="15" dy="15" />
 <space x="366" y="627" dx="13" dy="15" />
 <space x="442" y="627" dx="11" dy="15" />
 <space x="522" y="627" dx="10" dy="15" />
 <space x="604" y="627" dx="7" dy="15" />
 <space x="681" y="627" dx="6" dy="15" />
 <space x="752" y="627" dx="4" dy="15" />
 <space x="814" y="627" dx="2" dy="15" />
 <space x="866" y="627" dx="1" dy="15" />
 <space x="908" y="627" dx="0" dy="15" />
 <space x="941" y="627" dx="-2" dy="15" />
 <space x="965" y="627" dx="-3" dy="15" />
 <space x="982" y="627" dx="-3" dy="15" />
 <space x="994" y="627" dx="-3" dy="15" />
 <space x="1002" y="627" dx="-3" dy="15" />
 <space x="1007" y="627" dx="-3" dy="15" />
 <space x="1011" y="627" dx="-4" dy="15" />
 <space x="1013" y="627" dx="-4" dy="15" />
 <space x="1014" y="627" dx="-4" dy="15" />
 <space x="1015" y="627" dx="-4" dy="15" />
 <space x="1015" y="627" dx="-4" dy="15" />
 <space x="1015" y="627" dx="-3" dy="15" />
 <space x="1016" y="627" dx="-4" dy="15" />
 <space x="1016" y="627" dx="-4" dy="15" />
 <space x="1016" y="627" dx="-4" dy="15" />
 <space x="1016" y="627" dx="-3" dy="15" />
 <space x="1017" y="627" dx="-4" dy="15" />
 <space x="1017" y="627" dx="-4" dy="15" />
 <space x="1017" y="627" dx="-4" dy="15" />
 <space x="1017" y="627" dx="-4" dy="15" />
 <space x="1017" y="627" dx="-3" dy="15" />
 <space x="1018" y="627" dx="-4" dy="15" />
 <space x="1018" y="627" dx="-4" dy="15" />
 <space x="1018" y="627" dx="-4" dy="15" />
 <space x="1018" y="627" dx="-4" dy="15" />
 <space x="1018" y="627" dx="-4" dy="15" />
 <space x="1018" y="627" dx="-4" dy="15" />
 <space x="1018" y="627" dx="-4" dy="15" />
 <space x="1018" y="627" dx="-3" dy="15" />
 <box x="1016" y="627" dx="12" dy="15" value="\" numac="1" weights="97" achars="\" />
</line>
<line x="183" y="645" dx="861" dy="17" value="29">
 <space x="183" y="648" dx="-4" dy="15" />
 <space x="181" y="648" dx="-3" dy="15" />
 <space x="182" y="648" dx="-3" dy="15" />
 <space x="183" y="648" dx="-3" dy="15" />
 <space x="184" y="648" dx="-3" dy="15" />
 <space x="185" y="648" dx="-3" dy="15" />
 <space x="186" y="648" dx="-4" dy="15" />
 <space x="183" y="648" dx="12" dy="15" />
 <box x="183" y="648" dx="12" dy="15" value="/" numac="1" weights="97" achars="/" />
 <space x="196" y="648" dx="15" dy="15" />
 <space x="231" y="648" dx="16" dy="15" />
 <space x="285" y="648" dx="15" dy="15" />
 <space x="353" y="648" dx="13" dy="15" />
 <space x="430" y="648" dx="12" dy="15" />
 <space x="513" y="648" dx="10" dy="15" />
 <space x="597" y="648" dx="8" dy="15" />
 <space x="677" y="648" dx="6" dy="15" />
 <space x="750" y="648" dx="5" dy="15" />
 <space x="815" y="648" dx="3" dy="15" />
 <space x="870" y="648" dx="1" dy="15" />
 <space x="914" y="648" dx="0" dy="15" />
 <space x="949" y="648" dx="-1" dy="15" />
 <space x="975" y="648" dx="-2" dy="15" />
 <space x="994" y="648" dx="-3" dy="15" />
 <space x="1007" y="648" dx="-3" dy="15" />
 <space x="1016" y="648" dx="-3" dy="15" />
 <space x="1022" y="648" dx="-3" dy="15" />
 <space x="1026" y="648" dx="-4" dy="15" />
 <space x="1028" y="648" dx="-4" dy="15" />
 <space x="1029" y="648" dx="-3" dy="15" />
 <space x="1031" y="648" dx="-4" dy="15" />
 <space x="1031" y="648" dx="-4" dy="15" />
 <space x="1031" y="648" dx="-3" dy="15" />
 <space x="1032" y="648" dx="-4" dy="15" />
 <space x="1032" y="648" dx="-4" dy="15" />
 <space x="1032" y="648" dx="-4" dy="15" />
 <space x="1032" y="648" dx="-3" dy="15" />
 <space x="1033" y="648" dx="-4" dy="15" />
 <space x="1033" y="648" dx="-4" dy="15" />
 <space x="1033" y="648" dx="-4" dy="15" />
 <space x="1033" y="648" dx="-4" dy="15" />
 <space x="1033" y="648" dx="-4" dy="15" />
 <space x="1033" y="648" dx="-3" dy="15" />
 <space x="1034" y="648" dx="-4" dy="15" />
 <space x="1034" y="648" dx="-4" dy="15" />
 <space x="1034" y="648" dx="-4" dy="15" />
 <space x="1034" y="648" dx="-4" dy="15" />
 <space x="1034" y="648" dx="-4" dy="15" />
 <space x="1034" y="648" dx="-4" dy="15" />
 <space x="1034" y="648" dx="-4" dy="15" />
 <space x="1034" y="648" dx="-3" dy="15" />
 <box x="1032" y="648" dx="12" dy="15" value="\" numac="1" weights="100" achars="\" />
</line>
<line x="71" y="666" dx="989" dy="17" value="30">
 <space x="74" y="677" dx="-1" dy="7" />
 <space x="71" y="677" dx="20" dy="7" />
 <box x="71" y="677" dx="20" dy="7" value="r" numac="1" weights="97" achars="r" />
 <space x="92" y="669" dx="22" dy="15" />
 <space x="133" y="669" dx="14" dy="15" />
 <space x="162" y="669" dx="4" dy="15" />
 <box x="167" y="669" dx="13" dy="15" value="/" numac="1" weights="96" achars="/" />
 <space x="181" y="669" dx="15" dy="15" />
 <space x="216" y="669" dx="15" dy="15" />
 <space x="269" y="669" dx="14" dy="15" />
 <space x="336" y="669" dx="13" dy="15" />
 <space x="413" y="669" dx="12" dy="15" />
 <space x="496" y="669" dx="11" dy="15" />
 <space x="581" y="669" dx="9" dy="15" />
 <space x="664" y="669" dx="6" dy="15" />
 <space x="739" y="669" dx="5" dy="15" />
 <space x="807" y="669" dx="3" dy="15" />
 <space x="865" y="669" dx="1" dy="15" />
 <space x="912" y="669" dx="0" dy="15" />
 <space x="950" y="669" dx="-1" dy="15" />
 <space x="979" y="669" dx="-2" dy="15" />
 <space x="1000" y="669" dx="-2" dy="15" />
 <space x="1016" y="669" dx="-3" dy="15" />
 <space x="1027" y="669" dx="-4" dy="15" />
 <space x="1034" y="669" dx="-4" dy="15" />
 <space x="1038" y="669" dx="-3" dy="15" />
 <space x="1042" y="669" dx="-4" dy="15" />
 <space x="1044" y="669" dx="-4" dy="15" />
 <space x="1045" y="669" dx="-4" dy="15" />
 <space x="1046" y="669" dx="-4" dy="15" />
 <space x="1046" y="669" dx="-4" dy="15" />
 <space x="1046" y="669" dx="-4" dy="15" />
 <space x="1046" y="669" dx="-3" dy="15" />
 <space x="1047" y="669" dx="-4" dy="15" />
 <space x="1047" y="669" dx="-4" dy="15" />
 <space x="1047" y="669" dx="-4" dy="15" />
 <space x="1047" y="669" dx="-3" dy="15" />
 <space x="1048" y="669" dx="-4" dy="15" />
 <space x="1048" y="669" dx="-4" dy="15" />
 <space x="1048" y="669" dx="-4" dy="15" />
 <space x="1048" y="669" dx="-4" dy="15" />
 <space x="1048" y="669" dx="-4" dy="15" />
 <space x="1048" y="669" dx="-3" dy="15" />
 <space x="1049" y="669" dx="-4" dy="15" />
 <space x="1049" y="669" dx="-4" dy="15" />
 <space x="1049" y="669" dx="-4" dy="15" />
 <space x="1049" y="669" dx="-4" dy="15" />
 <space x="1049" y="669" dx="-4" dy="15" />
 <space x="1049" y="669" dx="-4" dy="15" />
 <space x="1049" y="669" dx="-4" dy="15" />
 <space x="1049" y="669" dx="-3" dy="15" />
 <box x="1047" y="669" dx="13" dy="15" value="\" numac="1" weights="97" achars="\" />
</line>
<line x="152" y="686" dx="923" dy="17" value="31">
 <space x="152" y="689" dx="-3" dy="15" />
 <space x="152" y="689" dx="-3" dy="15" />
 <space x="153" y="689" dx="-3" dy="15" />
 <space x="154" y="689" dx="-3" dy="15" />
 <space x="155" y="689" dx="-4" dy="15" />
 <space x="152" y="689" dx="12" dy="15" />
 <box x="152" y="689" dx="12" dy="15" value="/" numac="2" weights="97,94" achars="/,r" />
 <space x="165" y="689" dx="15" dy="15" />
 <space x="200" y="689" dx="15" dy="15" />
 <space x="252" y="689" dx="15" dy="15" />
 <space x="320" y="689" dx="13" dy="15" />
 <space x="397" y="689" dx="12" dy="15" />
 <space x="481" y="689" dx="10" dy="15" />
 <space x="566" y="689" dx="9" dy="15" />
 <space x="650" y="689" dx="7" dy="15" />
 <space x="728" y="689" dx="5" dy="15" />
 <space x="798" y="689" dx="4" dy="15" />
 <space x="860" y="689" dx="1" dy="15" />
 <space x="910" y="689" dx="1" dy="15" />
 <space x="952" y="689" dx="-1" dy="15" />
 <space x="984" y="689" dx="-2" dy="15" />
 <space x="1008" y="689" dx="-2" dy="15" />
 <space x="1026" y="689" dx="-3" dy="15" />
 <space x="1038" y="689" dx="-3" dy="15" />
 <space x="1047" y="689" dx="-4" dy="15" />
 <space x="1052" y="689" dx="-3" dy="15" />
 <space x="1056" y="689" dx="-4" dy="15" />
 <space x="1058" y="689" dx="-4" dy="15" />
 <space x="1060" y="689" dx="-4" dy="15" />
 <space x="1061" y="689" dx="-4" dy="15" />
 <space x="1062" y="689" dx="-4" dy="15" />
 <space x="1062" y="689" dx="-4" dy="15" />
 <space x="1062" y="689" dx="-4" dy="15" />
 <space x="1062" y="689" dx="-3" dy="15" />
 <space x="1063" y="689" dx="-4" dy="15" />
 <space x="1063" y="689" dx="-4" dy="15" />
 <space x="1063" y="689" dx="-4" dy="15" />
 <space x="1063" y="689" dx="-3" dy="15" />
 <space x="1064" y="689" dx="-4" dy="15" />
 <space x="1064" y="689" dx="-4" dy="15" />
 <space x="1064" y="689" dx="-4" dy="15" />
 <space x="1064" y="689" dx="-4" dy="15" />
 <space x="1064" y="689" dx="-4" dy="15" />
 <space x="1064" y="689" dx="-3" dy="15" />
 <space x="1065" y="689" dx="-4" dy="15" />
 <space x="1065" y="689" dx="-4" dy="15" />
 <space x="1065" y="689" dx="-4" dy="15" />
 <space x="1065" y="689" dx="-4" dy="15" />
 <space x="1065" y="689" dx="-4" dy="15" />
 <space x="1065" y="689" dx="-4" dy="15" />
 <space x="1065" y="689" dx="-4" dy="15" />
 <space x="1065" y="689" dx="-4" dy="15" />
 <space x="1065" y="689" dx="-3" dy="15" />
 <box x="1063" y="689" dx="12" dy="15" value="\" numac="1" weights="100" achars="\" />
</line>
<line x="136" y="704" dx="955" dy="20" value="32">
 <space x="136" y="710" dx="-3" dy="15" />
 <space x="136" y="710" dx="-3" dy="15" />
 <space x="137" y="710" dx="-3" dy="15" />
 <space x="138" y="710" dx="-3" dy="15" />
 <space x="139" y="710" dx="-4" dy="15" />
 <space x="136" y="710" dx="13" dy="15" />
 <box x="136" y="710" dx="13" dy="15" value="/" numac="2" weights="96,94" achars="/,r" />
 <space x="150" y="703" dx="16" dy="16" />
 <space x="186" y="703" dx="16" dy="16" />
 <space x="237" y="703" dx="14" dy="16" />
 <space x="295" y="703" dx="10" dy="16" />
 <space x="350" y="703" dx="7" dy="16" />
 <space x="396" y="703" dx="4" dy="16" />
 <space x="431" y="703" dx="1" dy="16" />
 <space x="454" y="703" dx="-1" dy="16" />
 <space x="468" y="703" dx="-3" dy="16" />
 <space x="475" y="703" dx="-3" dy="16" />
 <space x="478" y="703" dx="-3" dy="16" />
 <space x="480" y="703" dx="-4" dy="16" />
 <space x="480" y="703" dx="-3" dy="16" />
 <space x="481" y="703" dx="-4" dy="16" />
 <space x="481" y="703" dx="-4" dy="16" />
 <space x="481" y="703" dx="-3" dy="16" />
 <box x="479" y="703" dx="16" dy="16" value="_" />
 <box x="493" y="717" dx="16" dy="16" value="_" />
 <space x="510" y="709" dx="15" dy="15" />
 <space x="545" y="709" dx="15" dy="15" />
 <space x="596" y="709" dx="14" dy="15" />
 <space x="659" y="709" dx="12" dy="15" />
 <space x="728" y="709" dx="10" dy="15" />
 <space x="798" y="709" dx="7" dy="15" />
 <space x="863" y="709" dx="5" dy="15" />
 <space x="920" y="709" dx="3" dy="15" />
 <space x="967" y="709" dx="2" dy="15" />
 <space x="1004" y="709" dx="0" dy="15" />
 <space x="1031" y="709" dx="-1" dy="15" />
 <space x="1050" y="709" dx="-2" dy="15" />
 <space x="1062" y="709" dx="-3" dy="15" />
 <space x="1069" y="709" dx="-3" dy="15" />
 <space x="1074" y="709" dx="-4" dy="15" />
 <space x="1076" y="709" dx="-3" dy="15" />
 <space x="1078" y="709" dx="-4" dy="15" />
 <space x="1079" y="709" dx="-4" dy="15" />
 <space x="1079" y="709" dx="-4" dy="15" />
 <space x="1079" y="709" dx="-3" dy="15" />
 <space x="1080" y="709" dx="-4" dy="15" />
 <space x="1080" y="709" dx="-4" dy="15" />
 <space x="1080" y="709" dx="-4" dy="15" />
 <space x="1080" y="709" dx="-3" dy="15" />
 <space x="1081" y="709" dx="-4" dy="15" />
 <space x="1081" y="709" dx="-4" dy="15" />
 <space x="1081" y="709" dx="-4" dy="15" />
 <space x="1081" y="709" dx="-4" dy="15" />
 <space x="1081" y="709" dx="-3" dy="15" />
 <box x="1079" y="709" dx="12" dy="15" value="\" numac="1" weights="100" achars="\" />
</line>
<line x="214" y="761" dx="924" dy="25" value="33">
 <space x="214" y="774" dx="-4" dy="2" />
 <space x="212" y="774" dx="-3" dy="2" />
 <space x="212" y="774" dx="-3" dy="2" />
 <space x="213" y="774" dx="-4" dy="2" />
 <space x="213" y="774" dx="-3" dy="2" />
 <space x="215" y="774" dx="-4" dy="2" />
 <space x="215" y="774" dx="-3" dy="2" />
 <space x="216" y="774" dx="-3" dy="2" />
 <space x="217" y="774" dx="-4" dy="2" />
 <space x="214" y="774" dx="16" dy="2" />
 <box x="214" y="774" dx="16" dy="2" value="-" numac="1" weights="100" achars="-" />
 <box x="234" y="763" dx="6" dy="20" value="1" numac="1" weights="98" achars="1" />
 <space x="241" y="763" dx="17" dy="21" />
 <space x="278" y="763" dx="15" dy="21" />
 <space x="325" y="763" dx="12" dy="21" />
 <space x="371" y="763" dx="8" dy="21" />
 <space x="408" y="763" dx="3" dy="21" />
 <space x="431" y="763" dx="0" dy="21" />
 <space x="443" y="763" dx="-2" dy="21" />
 <space x="448" y="763" dx="-3" dy="21" />
 <space x="450" y="763" dx="-4" dy="21" />
 <space x="450" y="763" dx="-3" dy="21" />
 <box x="448" y="763" dx="14" dy="21" value="o" numac="2" weights="100,98" achars="o,0" />
 <space x="463" y="763" dx="17" dy="20" />
 <space x="500" y="763" dx="16" dy="20" />
 <space x="549" y="763" dx="12" dy="20" />
 <space x="597" y="763" dx="7" dy="20" />
 <space x="634" y="763" dx="4" dy="20" />
 <space x="659" y="763" dx="0" dy="20" />
 <space x="671" y="763" dx="-2" dy="20" />
 <space x="676" y="763" dx="-3" dy="20" />
 <space x="678" y="763" dx="-4" dy="20" />
 <space x="678" y="763" dx="-3" dy="20" />
 <box x="676" y="763" dx="7" dy="20" value="1" numac="1" weights="100" achars="1" />
 <space x="684" y="763" dx="15" dy="20" />
 <space x="718" y="763" dx="14" dy="20" />
 <space x="763" y="763" dx="12" dy="20" />
 <space x="810" y="763" dx="8" dy="20" />
 <space x="849" y="763" dx="4" dy="20" />
 <space x="876" y="763" dx="0" dy="20" />
 <space x="891" y="763" dx="-2" dy="20" />
 <space x="898" y="763" dx="-3" dy="20" />
 <space x="901" y="763" dx="-4" dy="20" />
 <space x="902" y="763" dx="-4" dy="20" />
 <space x="902" y="763" dx="-3" dy="20" />
 <box x="900" y="763" dx="13" dy="20" value="2" numac="2" weights="100,96" achars="2,l" />
 <space x="914" y="763" dx="17" dy="21" />
 <space x="951" y="763" dx="16" dy="21" />
 <space x="1000" y="763" dx="12" dy="21" />
 <space x="1047" y="763" dx="8" dy="21" />
 <space x="1085" y="763" dx="3" dy="21" />
 <space x="1109" y="763" dx="0" dy="21" />
 <space x="1121" y="763" dx="-2" dy="21" />
 <space x="1126" y="763" dx="-3" dy="21" />
 <space x="1128" y="763" dx="-4" dy="21" />
 <space x="1128" y="763" dx="-3" dy="21" />
 <box x="1126" y="763" dx="12" dy="21" value="3" numac="1" weights="100" achars="3" />
</line>
<line x="620" y="795" dx="30" dy="25" value="34">
 <space x="620" y="796" dx="-4" dy="20" />
 <space x="617" y="796" dx="-4" dy="20" />
 <space x="614" y="796" dx="-4" dy="20" />
 <space x="612" y="796" dx="-4" dy="20" />
 <space x="610" y="796" dx="-3" dy="20" />
 <space x="610" y="796" dx="-4" dy="20" />
 <space x="609" y="796" dx="-3" dy="20" />
 <space x="610" y="796" dx="-4" dy="20" />
 <space x="610" y="796" dx="-3" dy="20" />
 <space x="611" y="796" dx="-3" dy="20" />
 <space x="613" y="796" dx="-4" dy="20" />
 <space x="614" y="796" dx="-4" dy="20" />
 <space x="615" y="796" dx="-4" dy="20" />
 <space x="616" y="796" dx="-4" dy="20" />
 <space x="616" y="796" dx="-3" dy="20" />
 <space x="617" y="796" dx="-3" dy="20" />
 <space x="618" y="796" dx="-4" dy="20" />
 <space x="618" y="796" dx="-3" dy="20" />
 <space x="619" y="796" dx="-4" dy="20" />
 <space x="619" y="796" dx="-4" dy="20" />
 <space x="619" y="796" dx="-3" dy="20" />
 <space x="620" y="796" dx="-4" dy="20" />
 <space x="620" y="796" dx="-4" dy="20" />
 <space x="620" y="796" dx="-4" dy="20" />
 <space x="620" y="796" dx="-3" dy="20" />
 <space x="621" y="796" dx="-4" dy="20" />
 <space x="621" y="796" dx="-4" dy="20" />
 <space x="621" y="796" dx="-4" dy="20" />
 <space x="621" y="796" dx="-4" dy="20" />
 <space x="621" y="796" dx="-3" dy="20" />
 <space x="622" y="796" dx="-4" dy="20" />
 <space x="622" y="796" dx="-4" dy="20" />
 <space x="622" y="796" dx="-4" dy="20" />
 <space x="622" y="796" dx="-4" dy="20" />
 <space x="622" y="796" dx="-4" dy="20" />
 <space x="622" y="796" dx="-4" dy="20" />
 <space x="622" y="796" dx="-3" dy="20" />
 <space x="623" y="796" dx="-4" dy="20" />
 <space x="620" y="796" dx="14" dy="20" />
 <box x="620" y="796" dx="14" dy="20" value="R" numac="1" weights="100" achars="R" />
 <box x="636" y="796" dx="14" dy="20" value="R" numac="1" weights="100" achars="R" />
</line>
</block>
</page>
